aishield/__init__.py
aishield/base.py
aishield/cli.py
aishield/mapping.json
aishield/minify.py
aishield/test_runner.py
aishield/unminify.py
aishield/__pycache__/base.cpython-310.pyc
aishield/languages/__init__.py
aishield/languages/csharp/__init__.py
aishield/languages/csharp/adapter.py
aishield/languages/csharp/preserve_language.json
aishield/languages/csharp/__pycache__/adapter.cpython-310.pyc
aishield/languages/javascript/__init__.py
aishield/languages/javascript/adapter.py
aishield/languages/javascript/keywords_javascript.json
aishield/languages/javascript/preserve_language.json
aishield/languages/javascript/__pycache__/adapter.cpython-310.pyc
code_defender-1.1.7.dist-info/licenses/LICENSE
code_defender-1.1.7.dist-info/METADATA
code_defender-1.1.7.dist-info/WHEEL
code_defender-1.1.7.dist-info/entry_points.txt
code_defender-1.1.7.dist-info/top_level.txt
code_defender-1.1.7.dist-info/RECORD
