Metadata-Version: 2.4
Name: code-defender
Version: 1.1.7
Summary: Intelligent code obfuscator to protect your code from AI-based analysis and reverse engineering
Author: AIShield Contributors
License-Expression: BSD-3-Clause
Project-URL: Homepage, https://github.com/webinadvance/aishield
Project-URL: Documentation, https://github.com/webinadvance/aishield#readme
Project-URL: Repository, https://github.com/webinadvance/aishield.git
Project-URL: Bug Tracker, https://github.com/webinadvance/aishield/issues
Keywords: obfuscation,code-protection,ai-detection,code-security,reverse-engineering
Classifier: Development Status :: 4 - Beta
Classifier: Intended Audience :: Developers
Classifier: Programming Language :: Python :: 3
Classifier: Programming Language :: Python :: 3.8
Classifier: Programming Language :: Python :: 3.9
Classifier: Programming Language :: Python :: 3.10
Classifier: Programming Language :: Python :: 3.11
Classifier: Programming Language :: Python :: 3.12
Classifier: Operating System :: OS Independent
Classifier: Topic :: Software Development :: Libraries :: Python Modules
Classifier: Topic :: Utilities
Requires-Python: >=3.8
License-File: LICENSE
Requires-Dist: pyperclip>=1.8.0
Requires-Dist: tree-sitter>=0.25.0
Requires-Dist: tree-sitter-javascript>=0.25.0
Requires-Dist: tree-sitter-c-sharp>=0.23.0
Provides-Extra: dev
Requires-Dist: pytest>=7.0; extra == "dev"
Requires-Dist: pytest-cov>=3.0; extra == "dev"
Requires-Dist: black>=22.0; extra == "dev"
Requires-Dist: flake8>=4.0; extra == "dev"
Requires-Dist: mypy>=0.950; extra == "dev"
Dynamic: license-file
